async_fifo/async_fifo.v
module async_fifo #( parameter WIDTH =32 , DEPTH = 8 , ADDR =4) (
input wr_clk ,
input rst_n ,
input rd_clk ,
input wr ,
input rd ,
input [WIDTH-1:0] din ,
output reg [WIDTH-1:0] dout ,
output empty ,
output full );

reg [ADDR-1:0]wr_ptr_b,rd_ptr_b,wr_ptr_g_s1,wr_ptr_g_s2,rd_ptr_g_s1,rd_ptr_g_s2;

wire  [ADDR-1:0]wr_ptr_g,rd_ptr_g;

reg [WIDTH-1:0] mem [DEPTH-1:0];


// write 
always@(posedge wr_clk or negedge rst_n)begin 
if(!rst_n) begin wr_ptr_b <= 0; end
else begin
  if(wr && !full)begin 
  mem[wr_ptr_b[2:0]] <= din;
  wr_ptr_b <= wr_ptr_b + 1;
  end
end
end

// read 
always@(posedge rd_clk or negedge rst_n)begin 
if(!rst_n) begin rd_ptr_b <= 0; dout <= 0; end
else begin
  if(rd && !empty)begin 
  dout <= mem[rd_ptr_b[2:0]]; 
  rd_ptr_b <= rd_ptr_b + 1;
  end
end
end

//binary to gray 
assign wr_ptr_g = wr_ptr_b ^ (wr_ptr_b >>1);

assign rd_ptr_g = rd_ptr_b ^ (rd_ptr_b >>1);

//sync for rd side 
always@(posedge rd_clk or negedge rst_n)begin
if(!rst_n) begin wr_ptr_g_s1 <= 0;  wr_ptr_g_s2 <= 0;end
else begin 
wr_ptr_g_s1 <= wr_ptr_g;
wr_ptr_g_s2 <= wr_ptr_g_s1;
end
end

//sync for wr side
always@(posedge wr_clk or negedge rst_n)begin
if(!rst_n) begin rd_ptr_g_s1 <= 0;  rd_ptr_g_s2 <= 0;end
else begin 
rd_ptr_g_s1 <= rd_ptr_g;
rd_ptr_g_s2 <= rd_ptr_g_s1;
end
end


// full and empty
assign empty = (wr_ptr_g_s2 == rd_ptr_g);

assign full = (wr_ptr_g == { ~rd_ptr_g_s2 [ADDR-1:ADDR-2] , rd_ptr_g_s2 [ADDR-3:0]});

endmodule

async_fifo/async_fifo_tb.v
`timescale 1ns/1ps

module async_fifo_tb;

parameter WIDTH = 32;
parameter DEPTH = 8;
parameter ADDR  = 3;

reg wr_clk;
reg rd_clk;
reg rst_n;
reg wr;
reg rd;

reg  [WIDTH-1:0] din;
wire [WIDTH-1:0] dout;
wire empty;
wire full;

async_fifo #(
    .WIDTH(WIDTH),
    .DEPTH(DEPTH),
    .ADDR(ADDR)
) DUT (
    .wr_clk(wr_clk),
    .rd_clk(rd_clk),
    .rst_n(rst_n),
    .wr(wr),
    .rd(rd),
    .din(din),
    .dout(dout),
    .empty(empty),
    .full(full)
);

// ---------------- Clocks ----------------
always #5   wr_clk = ~wr_clk;   // 100 MHz
always #2.5 rd_clk = ~rd_clk;   // 200 MHz

// ---------------- Dump ----------------
initial begin
    $dumpfile("async_fifo.vcd");
    $dumpvars(0, async_fifo_tb);
end

// ---------------- Reset Task ----------------
task reset;
begin
    rst_n = 0;
    #20;
    rst_n = 1;
end
endtask

// ---------------- Write Task ----------------
task write(input [WIDTH-1:0] data);
begin
    @(posedge wr_clk);
    if (!full) begin
        din = data;
        wr  = 1;
    end
    @(posedge wr_clk);
    wr = 0;
end
endtask

// ---------------- Read Task ----------------
task read;
begin
    @(posedge rd_clk);
    if (!empty)
        rd = 1;
    @(posedge rd_clk);
    rd = 0;
end
endtask

// ---------------- Initial ----------------
integer i;

initial begin
    // init
    wr_clk = 0;
    rd_clk = 0;
    wr = 0;
    rd = 0;
    rst_n = 1;

    // reset
    reset();

    // Write one value
    write(32'd55);

    // Read one value
    read();

    // -------- Fill FIFO to FULL --------
    for (i = 0; i < DEPTH; i = i + 1) begin
        write($random);
    end

    // -------- Empty FIFO --------
    for (i = 0; i < DEPTH; i = i + 1) begin
        read();
    end

    #200;
    $finish;
end

endmodule

async_fifo/async_fifo.vcd
$version Generated by VerilatedVcd $end
$timescale 1ps $end
 $scope module TOP $end
  $scope module async_fifo_tb $end
   $var wire 32 = WIDTH [31:0] $end
   $var wire 32 > DEPTH [31:0] $end
   $var wire 32 ? ADDR [31:0] $end
   $var wire 1 9 wr_clk $end
   $var wire 1 : rd_clk $end
   $var wire 1 # rst_n $end
   $var wire 1 $ wr $end
   $var wire 1 % rd $end
   $var wire 32 & din [31:0] $end
   $var wire 32 ( dout [31:0] $end
   $var wire 1 ; empty $end
   $var wire 1 , full $end
   $var wire 32 ' i [31:0] $end
   $scope module DUT $end
    $var wire 32 = WIDTH [31:0] $end
    $var wire 32 > DEPTH [31:0] $end
    $var wire 32 ? ADDR [31:0] $end
    $var wire 1 9 wr_clk $end
    $var wire 1 # rst_n $end
    $var wire 1 : rd_clk $end
    $var wire 1 $ wr $end
    $var wire 1 % rd $end
    $var wire 32 & din [31:0] $end
    $var wire 32 ( dout [31:0] $end
    $var wire 1 ; empty $end
    $var wire 1 , full $end
    $var wire 3 - wr_ptr_b [2:0] $end
    $var wire 3 ) rd_ptr_b [2:0] $end
    $var wire 3 * wr_ptr_g_s1 [2:0] $end
    $var wire 3 + wr_ptr_g_s2 [2:0] $end
    $var wire 3 . rd_ptr_g_s1 [2:0] $end
    $var wire 3 / rd_ptr_g_s2 [2:0] $end
    $var wire 3 0 wr_ptr_g [2:0] $end
    $var wire 3 < rd_ptr_g [2:0] $end
    $var wire 32 1 mem[0] [31:0] $end
    $var wire 32 2 mem[1] [31:0] $end
    $var wire 32 3 mem[2] [31:0] $end
    $var wire 32 4 mem[3] [31:0] $end
    $var wire 32 5 mem[4] [31:0] $end
    $var wire 32 6 mem[5] [31:0] $end
    $var wire 32 7 mem[6] [31:0] $end
    $var wire 32 8 mem[7] [31:0] $end
   $upscope $end
  $upscope $end
 $upscope $end
$enddefinitions $end


#0
0#
0$
0%
b00000000000000000000000000000000 &
b00000000000000000000000000000000 '
b00000000000000000000000000000000 (
b000 )
b000 *
b000 +
0,
b000 -
b000 .
b000 /
b000 0
b00000000000000000000000000000000 1
b00000000000000000000000000000000 2
b00000000000000000000000000000000 3
b00000000000000000000000000000000 4
b00000000000000000000000000000000 5
b00000000000000000000000000000000 6
b00000000000000000000000000000000 7
b00000000000000000000000000000000 8
09
0:
1;
b000 <
b00000000000000000000000000100000 =
b00000000000000000000000000001000 >
b00000000000000000000000000000011 ?
#2500
1:
#5000
19
0:
#7500
1:
#10000
09
0:
#12500
1:
#15000
19
0:
#17500
1:
#20000
1#
09
0:
#22500
1:
#25000
1$
b00000000000000000000000000110111 &
b001 -
b001 0
b00000000000000000000000000110111 1
19
0:
#27500
b001 *
1:
#30000
09
0:
#32500
b001 +
1:
0;
#35000
0$
19
0:
#37500
1%
b00000000000000000000000000110111 (
b001 )
1:
1;
b001 <
#40000
09
0:
#42500
0%
1:
#45000
1$
b01111001011101100111001111000100 &
b010 -
b001 .
b011 0
b01111001011101100111001111000100 2
19
0:
#47500
b011 *
1:
#50000
09
0:
#52500
b011 +
1:
0;
#55000
0$
b00000000000000000000000000000001 '
b001 /
19
0:
#57500
1:
#60000
09
0:
#62500
1:
#65000
1$
b00001011000111100101110110011100 &
b011 -
b010 0
b00001011000111100101110110011100 3
19
0:
#67500
b010 *
1:
#70000
09
0:
#72500
b010 +
1:
#75000
0$
b00000000000000000000000000000010 '
19
0:
#77500
1:
#80000
09
0:
#82500
1:
#85000
1$
b10011110111111011101010100000010 &
b100 -
b110 0
b10011110111111011101010100000010 4
19
0:
#87500
b110 *
1:
#90000
09
0:
#92500
b110 +
1:
#95000
0$
b00000000000000000000000000000011 '
19
0:
#97500
1:
#100000
09
0:
#102500
1:
#105000
1$
b01001000110000101110000011100100 &
1,
b101 -
b111 0
b01001000110000101110000011100100 5
19
0:
#107500
b111 *
1:
#110000
09
0:
#112500
b111 +
1:
#115000
0$
b00000000000000000000000000000100 '
19
0:
#117500
1:
#120000
09
0:
#122500
1:
#125000
19
0:
#127500
1:
#130000
09
0:
#132500
1:
#135000
b00000000000000000000000000000101 '
19
0:
#137500
1:
#140000
09
0:
#142500
1:
#145000
19
0:
#147500
1:
#150000
09
0:
#152500
1:
#155000
b00000000000000000000000000000110 '
19
0:
#157500
1:
#160000
09
0:
#162500
1:
#165000
19
0:
#167500
1:
#170000
09
0:
#172500
1:
#175000
b00000000000000000000000000000111 '
19
0:
#177500
1:
#180000
09
0:
#182500
1:
#185000
19
0:
#187500
1:
#190000
09
0:
#192500
1:
#195000
b00000000000000000000000000001000 '
19
0:
#197500
1%
b01111001011101100111001111000100 (
b010 )
1:
b011 <
#200000
09
0:
#202500
0%
b00000000000000000000000000000001 '
1:
#205000
b011 .
19
0:
#207500
1%
b00001011000111100101110110011100 (
b011 )
1:
b010 <
#210000
09
0:
#212500
0%
b00000000000000000000000000000010 '
1:
#215000
0,
b010 .
b011 /
19
0:
#217500
1%
b10011110111111011101010100000010 (
b100 )
1:
b110 <
#220000
09
0:
#222500
0%
b00000000000000000000000000000011 '
1:
#225000
b110 .
b010 /
19
0:
#227500
1%
b01001000110000101110000011100100 (
b101 )
1:
1;
b111 <
#230000
09
0:
#232500
0%
b00000000000000000000000000000100 '
1:
#235000
b111 .
b110 /
19
0:
#237500
1:
#240000
09
0:
#242500
b00000000000000000000000000000101 '
1:
#245000
b111 /
19
0:
#247500
1:
#250000
09
0:
#252500
b00000000000000000000000000000110 '
1:
#255000
19
0:
#257500
1:
#260000
09
0:
#262500
b00000000000000000000000000000111 '
1:
#265000
19
0:
#267500
1:
#270000
09
0:
#272500
b00000000000000000000000000001000 '
1:
